spyip/__init__.py
spyip/exceptions.py
spyip/models.py
spyip/backends/asynchronous.py
spyip/backends/synchronous.py
spyip-0.3.0.dist-info/METADATA
spyip-0.3.0.dist-info/WHEEL
spyip-0.3.0.dist-info/licenses/LICENSE
spyip-0.3.0.dist-info/RECORD
