Metadata-Version: 2.1
Name: spyip
Version: 0.3.0
Summary: A simple IP lookup tool written in Python with concurrency support.
Project-URL: Homepage, https://github.com/Almas-Ali/SpyIP
Project-URL: Documentation, https://github.com/Almas-Ali/SpyIP#readme
Project-URL: Repository, https://github.com/Almas-Ali/spyip
Project-URL: Bug Tracker, https://github.com/Almas-Ali/SpyIP/issues
Author-email: "Md. Almas Ali" <almaspr3@gmail.com>
Maintainer-email: "Md. Almas Ali" <almaspr3@gmail.com>
License: The MIT License (MIT)
License-File: LICENSE
Keywords: ip,ip-geolocation,ip-info,ip-info-api,ip-info-api-python,ip-information,ip-location,ip-lookup,ipv4,ipv6,lookup,python,python-package,simple,utility
Classifier: Development Status :: 5 - Production/Stable
Classifier: Intended Audience :: Developers
Classifier: Intended Audience :: Information Technology
Classifier: License :: OSI Approved :: MIT License
Classifier: Programming Language :: Python
Classifier: Programming Language :: Python :: 3
Classifier: Programming Language :: Python :: 3 :: Only
Classifier: Programming Language :: Python :: 3.7
Classifier: Programming Language :: Python :: 3.8
Classifier: Programming Language :: Python :: 3.9
Classifier: Programming Language :: Python :: 3.10
Classifier: Programming Language :: Python :: 3.11
Classifier: Programming Language :: Python :: 3.12
Classifier: Topic :: Internet
Requires-Python: >=3.7
Requires-Dist: attrs==23.2.0
Requires-Dist: httpx==0.26.0
